decoupler_mcp/__init__.py
decoupler_mcp/cli.py
decoupler_mcp/schema/__init__.py
decoupler_mcp/schema/inference.py
decoupler_mcp/server/__init__.py
decoupler_mcp/server/inference.py
decoupler_mcp/server/rag.py
decoupler_mcp-0.4.0.dist-info/METADATA
decoupler_mcp-0.4.0.dist-info/WHEEL
decoupler_mcp-0.4.0.dist-info/entry_points.txt
decoupler_mcp-0.4.0.dist-info/RECORD
