Metadata-Version: 2.4
Name: decoupler-mcp
Version: 0.4.0
Summary: Natural language interface for biological activities analysis with decoupler through MCP.
Project-URL: Homepage, http://scmcphub.org/
Project-URL: Repository, https://github.com/scmcphub/decoupler-mcp
Project-URL: Documentation, https://docs.scmcphub.org/
Author-email: shuang <hsh-me@outlook.com>
Keywords: AI,agent,bioinformatics,llm,mcp,model context protocol,scRNA-seq,single cell
Requires-Python: >=3.10
Requires-Dist: agno
Requires-Dist: dcor
Requires-Dist: decoupler>=2.0.1
Requires-Dist: fastmcp>=2.3.5
Requires-Dist: lancedb
Requires-Dist: nest-asyncio
Requires-Dist: scanpy
Requires-Dist: scmcp-shared>=0.5.0
